CHANGELOG.rst
LICENSE.txt
MANIFEST.in
README.rst
requirements.txt
setup.cfg
setup.py
docs/Makefile
docs/make.bat
docs/source/api.rst
docs/source/autocas.rst
docs/source/changelog.rst
docs/source/conf.py
docs/source/index.rst
docs/source/installation.rst
docs/source/interfaces.rst
docs/source/plots.rst
docs/source/quickstart.rst
docs/source/readme.rst
docs/source/set_up.rst
docs/source/usage.rst
scine_autocas/__init__.py
scine_autocas/__main__.py
scine_autocas/_version.py
scine_autocas.egg-info/PKG-INFO
scine_autocas.egg-info/SOURCES.txt
scine_autocas.egg-info/dependency_links.txt
scine_autocas.egg-info/entry_points.txt
scine_autocas.egg-info/not-zip-safe
scine_autocas.egg-info/requires.txt
scine_autocas.egg-info/top_level.txt
scine_autocas/cas_selection/__init__.py
scine_autocas/cas_selection/active_space.py
scine_autocas/cas_selection/active_space_handler.py
scine_autocas/cas_selection/autocas.py
scine_autocas/cas_selection/cas_combination.py
scine_autocas/cas_selection/diagnostics.py
scine_autocas/cas_selection/large_active_spaces.py
scine_autocas/interfaces/__init__.py
scine_autocas/interfaces/interface.py
scine_autocas/interfaces/chronusq/__init__.py
scine_autocas/interfaces/chronusq/chronusq.py
scine_autocas/interfaces/chronusq/cq_hdf5_reader.py
scine_autocas/interfaces/molcas/__init__.py
scine_autocas/interfaces/molcas/environment.py
scine_autocas/interfaces/molcas/input_handler.py
scine_autocas/interfaces/molcas/molcas.py
scine_autocas/interfaces/molcas/molcas_hdf5_utils.py
scine_autocas/interfaces/pyscf/__init__.py
scine_autocas/interfaces/pyscf/pyscf.py
scine_autocas/interfaces/qcmaquis_utils/__init__.py
scine_autocas/interfaces/qcmaquis_utils/environment.py
scine_autocas/interfaces/qcmaquis_utils/qcmaquis_hdf5_dataset.py
scine_autocas/interfaces/qcmaquis_utils/qcmaquis_hdf5_utils.py
scine_autocas/interfaces/qcmaquis_utils/qcmaquis_orbital_rdm_builder.py
scine_autocas/interfaces/qcmaquis_utils/qcmaquis_utils.py
scine_autocas/interfaces/serenity/__init__.py
scine_autocas/interfaces/serenity/serenity.py
scine_autocas/io/__init__.py
scine_autocas/io/cli.py
scine_autocas/io/file_handler.py
scine_autocas/io/input_handler.py
scine_autocas/io/logger.py
scine_autocas/io/actions/__init__.py
