Metadata-Version: 2.1
Name: scine-autocas
Version: 3.0.0
Summary: Automated active space selection quantum chemical software
Home-page: https://www.scine.ethz.ch
Author: ETH Zurich, Department of Chemistry and Applied Biosciences, Reiher Group
Author-email: scine@phys.chem.ethz.ch
License: BSD (3-clause)
Classifier: Programming Language :: Python
Classifier: Development Status :: 5 - Production/Stable
Classifier: Intended Audience :: Science/Research
Classifier: License :: OSI Approved :: BSD License
Classifier: Natural Language :: English
Classifier: Topic :: Scientific/Engineering :: Chemistry
Requires-Python: >=3.8
License-File: LICENSE.txt
